wafl_llm/__init_.py
wafl_llm/__main__.py
wafl_llm/command_line.py
wafl_llm/config.json
wafl_llm/config.properties
wafl_llm/configuration.py
wafl_llm/configuration_handler.py
wafl_llm/default_handler.py
wafl_llm/entailer_handler.py
wafl_llm/llama3_handler.py
wafl_llm/llm_handler.py
wafl_llm/llm_handler_factory.py
wafl_llm/mistral_handler.py
wafl_llm/phi35_4k_cpu_handler.py
wafl_llm/phi35_4k_handler.py
wafl_llm/phi3_4k_cpu_handler.py
wafl_llm/phi3_4k_handler.py
wafl_llm/sentence_embedder_handler.py
wafl_llm/speaker_embeddings.py
wafl_llm/speaker_handler.py
wafl_llm/tinkering.py
wafl_llm/variables.py
wafl_llm/whisper_handler.py
wafl_llm-0.1.2.dist-info/METADATA
wafl_llm-0.1.2.dist-info/WHEEL
wafl_llm-0.1.2.dist-info/entry_points.txt
wafl_llm-0.1.2.dist-info/top_level.txt
wafl_llm-0.1.2.dist-info/RECORD
