Metadata-Version: 2.1
Name: wafl_llm
Version: 0.1.2
Summary: A hybrid chatbot - LLM side.
Home-page: http://github.com/fractalego/wafl_llm
Author: Alberto Cetoli
Author-email: Alberto Cetoli <alberto@fractalego.io>
License: MIT License
Project-URL: Homepage, https://github.com/fractalego/wafl_llm
Project-URL: Issues, https://github.com/fractalego/wafl_llm/issues
Classifier: Programming Language :: Python :: 3
Classifier: License :: OSI Approved :: MIT License
Classifier: Operating System :: OS Independent
Requires-Python: >=3.11
